passivetotal/__init__.py
passivetotal/__main__.py
passivetotal/_version.py
passivetotal/api.py
passivetotal/config.py
passivetotal/response.py
passivetotal/analyzer/__init__.py
passivetotal/analyzer/_common.py
passivetotal/analyzer/articles.py
passivetotal/analyzer/components.py
passivetotal/analyzer/cookies.py
passivetotal/analyzer/enrich.py
passivetotal/analyzer/hostname.py
passivetotal/analyzer/hostpairs.py
passivetotal/analyzer/illuminate.py
passivetotal/analyzer/ip.py
passivetotal/analyzer/pdns.py
passivetotal/analyzer/projects.py
passivetotal/analyzer/services.py
passivetotal/analyzer/ssl.py
passivetotal/analyzer/summary.py
passivetotal/analyzer/trackers.py
passivetotal/analyzer/whois.py
passivetotal/analyzer/illuminate/__init__.py
passivetotal/analyzer/illuminate/asi.py
passivetotal/analyzer/illuminate/cti.py
passivetotal/analyzer/illuminate/reputation.py
passivetotal/analyzer/illuminate/vuln.py
passivetotal/cli/__init__.py
passivetotal/cli/client.py
passivetotal/cli/config.py
passivetotal/cli/info.py
passivetotal/common/__init__.py
passivetotal/common/const.py
passivetotal/common/exceptions.py
passivetotal/common/utilities.py
passivetotal/libs/__init__.py
passivetotal/libs/account.py
passivetotal/libs/actions.py
passivetotal/libs/articles.py
passivetotal/libs/artifacts.py
passivetotal/libs/attributes.py
passivetotal/libs/cards.py
passivetotal/libs/cookies.py
passivetotal/libs/dns.py
passivetotal/libs/enrichment.py
passivetotal/libs/generic.py
passivetotal/libs/host_attributes.py
passivetotal/libs/illuminate.py
passivetotal/libs/intelligence.py
passivetotal/libs/monitor.py
passivetotal/libs/projects.py
passivetotal/libs/services.py
passivetotal/libs/ssl.py
passivetotal/libs/trackers.py
passivetotal/libs/whois.py
tests/__init__.py
tests/conf.py
tests/test_account.py
tests/test_actions.py
tests/test_articles.py
tests/test_artifacts.py
tests/test_attributes.py
tests/test_cards.py
tests/test_cookies.py
tests/test_dns.py
tests/test_enrichment.py
passivetotal-2.5.9.dist-info/LICENSE
passivetotal-2.5.9.dist-info/METADATA
passivetotal-2.5.9.dist-info/WHEEL
passivetotal-2.5.9.dist-info/entry_points.txt
passivetotal-2.5.9.dist-info/top_level.txt
passivetotal-2.5.9.dist-info/RECORD
