Metadata-Version: 2.1
Name: passivetotal
Version: 2.5.9
Summary: Library for the RiskIQ PassiveTotal and Illuminate API
Home-page: https://github.com/passivetotal/python_api
Download-URL: https://github.com/passivetotal/python_api/archive/master.zip
Author: RiskIQ
Author-email: admin@passivetotal.org
License: GPLv2
Keywords: threats,research,analysis
Platform: UNKNOWN
Provides-Extra: pandas
License-File: LICENSE
